autofill/__init__.py
autofill/cli.py
autofill/forms.py
autofill/utils/__init__.py
autofill/utils/_exceptions.py
autofill/utils/_path.py
autofill/utils/_warnings.py
autofill/utils/coloring_utils.py
autofill/utils/environ_utils.py
autofill/utils/form_utils.py
autofill/utils/generic_utils.py
autofill/utils/monitor_utils.py
Auto_Fill_In-0.0.1.dist-info/LICENSE
Auto_Fill_In-0.0.1.dist-info/METADATA
Auto_Fill_In-0.0.1.dist-info/WHEEL
Auto_Fill_In-0.0.1.dist-info/entry_points.txt
Auto_Fill_In-0.0.1.dist-info/top_level.txt
Auto_Fill_In-0.0.1.dist-info/RECORD
