Metadata-Version: 2.1
Name: Auto-Fill-In
Version: 0.0.1
Summary: Auto fill in your form using your saved information (or answer on the spot).
Home-page: UNKNOWN
Author: Shuto Iwasaki
Author-email: cabernet.rock@gmail.com
License: MIT
Project-URL: Bug Reports, https://github.com/iwasakishuto/Auto-Fill-In/issues
Project-URL: Source Code, https://github.com/iwasakishuto/Auto-Fill-In
Project-URL: Say Thanks!, https://twitter.com/cabernet_rock
Platform: UNKNOWN
Classifier: Development Status :: 3 - Alpha
Classifier: Environment :: Console
Classifier: Intended Audience :: Other Audience
Classifier: License :: OSI Approved :: MIT License
Classifier: Programming Language :: Python :: 3
Classifier: Programming Language :: Python :: 3.8
Classifier: Topic :: Software Development :: Libraries :: Python Modules
Requires-Python: >=3.7
Requires-Dist: Translation-Gummy (>=3.4.1)
Requires-Dist: imgcat (>=0.5.0)
Provides-Extra: tests
Requires-Dist: pytest ; extra == 'tests'
